LICENSE
README.md
setup.py
slmd/__init__.py
slmd/cmd.py
slmd/slmd.py
slmd/test.py
slmd.egg-info/PKG-INFO
slmd.egg-info/SOURCES.txt
slmd.egg-info/dependency_links.txt
slmd.egg-info/entry_points.txt
slmd.egg-info/top_level.txt
slmd.egg-info/zip-safe