Metadata-Version: 1.2
Name: slmd
Version: 0.1.5
Summary: Markdown list sorter
Home-page: http://github.com/lqez/slmd
Author: Park Hyunwoo
Author-email: ez.amiryo@gmail.com
Maintainer: Park Hyunwoo
Maintainer-email: ez.amiryo@gmail.com
License: UNKNOWN
Platform: UNKNOWN
Classifier: Topic :: Terminals
Classifier: Topic :: Utilities
Classifier: Environment :: Console
Classifier: Development Status :: 4 - Beta
Classifier: Intended Audience :: Developers
Classifier: Intended Audience :: System Administrators
Classifier: Programming Language :: Python
Classifier: Programming Language :: Python :: 3.6
Classifier: Programming Language :: Python :: 3.7
Classifier: Programming Language :: Python :: 3.8
Classifier: Programming Language :: Python :: 3.9
Classifier: License :: OSI Approved :: MIT License
